libnn/__init__.py
libnn/dispatch.py
libnn/networks/__init__.py
libnn/networks/lstms.py
libnn/networks/resnets.py
libnn/toolbox/__init__.py
libnn/toolbox/dataloader.py
libnn/toolbox/datasplit.py
libnn/toolbox/funcs.py
libnn-0.0.6.dist-info/METADATA
libnn-0.0.6.dist-info/WHEEL
libnn-0.0.6.dist-info/top_level.txt
libnn-0.0.6.dist-info/RECORD
