Metadata-Version: 2.1
Name: libnn
Version: 0.0.6
Summary: left blank
Home-page: https://github.com/soonyenju/libnn
Author: Songyan Zhu
Author-email: soonyenju@foxmail.com
License: MIT Licence
Keywords: resnet,run nn
Platform: any
